tariff_lu/__about__.py
tariff_lu/__init__.py
tariff_lu-0.0.1.dist-info/METADATA
tariff_lu-0.0.1.dist-info/WHEEL
tariff_lu-0.0.1.dist-info/licenses/LICENSE.txt
tariff_lu-0.0.1.dist-info/RECORD
